{
	"page": 1,
	"object": [
		{
			"id": 1,
			"type": "text",
			"area": [
				[
					75,
					4
				],
				[
					490,
					4
				],
				[
					490,
					104
				],
				[
					75,
					104
				]
			],
			"content": "설치 및 실행"
		},
		{
			"id": 2,
			"type": "text",
			"area": [
				[
					74,
					168
				],
				[
					217,
					168
				],
				[
					217,
					265
				],
				[
					74,
					265
				]
			],
			"content": "설치"
		},
		{
			"id": 3,
			"type": "text",
			"area": [
				[
					76,
					340
				],
				[
					1614,
					340
				],
				[
					1614,
					760
				],
				[
					76,
					760
				]
			],
			"content": "설치는 두 가지 방법이 있든데, 첫 번째는 Anaconda와 함께 설치하 논 방법이 있다: Anaconda틀 설치할 때 Jupyter Notebook도 같이 설치하면 된다: Anaconda와 같은 역할울 하는 Miniconda 사용법은 여기름 참조하 도록 한다"
		},
		{
			"id": 4,
			"type": "text",
			"area": [
				[
					78,
					834
				],
				[
					1580,
					834
				],
				[
					1580,
					995
				],
				[
					78,
					995
				]
			],
			"content": "Anadonda틀 설치하는 방법 외에 기본적으로 pip은 Jupyter 패키 지 설치름 지원한다. 설치 방법은 다른 패키지 설치 방법과 똑같다:"
		},
		{
			"id": 5,
			"type": "text",
			"area": [
				[
					74,
					1064
				],
				[
					1477,
					1064
				],
				[
					1477,
					1144
				],
				[
					74,
					1144
				]
			],
			"content": "파이선3과 2틀 구분지어야 한다면 pip 대신 pip3틀 사용하다:"
		}
	]
}